README.md
setup.py
MFEprimer/__init__.py
MFEprimer/chilli/CairoNumberWidth.py
MFEprimer/chilli/DegenerateSeqConvetor.py
MFEprimer/chilli/FastaFormatParser.py
MFEprimer/chilli/FastaIterator.py
MFEprimer/chilli/FastaRemoveRedundant.py
MFEprimer/chilli/FastaSimpleFormatParser.py
MFEprimer/chilli/GelMobility.py
MFEprimer/chilli/MFEprimerParser.py
MFEprimer/chilli/PenultimateTable.py
MFEprimer/chilli/Seq.py
MFEprimer/chilli/SeqCheck.py
MFEprimer/chilli/ThermodynamicsParameters.py
MFEprimer/chilli/TmDeltaG.py
MFEprimer/chilli/__init__.py
MFEprimer/chilli/chilli.py
MFEprimer/chilli/conv_shelve_json.py
MFEprimer/chilli/mve.py
MFEprimer/chilli/ve.py
MFEprimer_linux.egg-info/PKG-INFO
MFEprimer_linux.egg-info/SOURCES.txt
MFEprimer_linux.egg-info/dependency_links.txt
MFEprimer_linux.egg-info/top_level.txt
scripts/MFE_primer.py
scripts/UniFastaFormat.py
scripts/faToTwoBit
scripts/mfe_index_db.py
scripts/twoBitToFa