Metadata-Version: 1.0
Name: MFEprimer_linux
Version: 2.1.1
Summary: A fast thermodynamics-based program for checking PCR primer specificity (linux-specific)
Home-page: https://github.com/nick-youngblut/MFEprimer_linux
Author: Nick Youngblut
Author-email: nyoungb2@gmail.com
License: MIT license
Platform: UNKNOWN
